{
  "questIDHigh:4": 0,
  "preRequisites:9": {
    "0:10": {
      "questIDHigh:4": 0,
      "questIDLow:4": 176
    }
  },
  "questIDLow:4": 1005,
  "properties:10": {
    "betterquesting:10": {
      "snd_complete:8": "random.levelup",
      "taskLogic:8": "AND",
      "partySingleReward:1": 0,
      "visibility:8": "NORMAL",
      "isMain:1": 1,
      "simultaneous:1": 0,
      "icon:10": {
        "id:8": "gregtech:gt.metaitem.01",
        "Count:3": 1,
        "Damage:2": 2056,
        "OreDict:8": ""
      },
      "snd_update:8": "random.levelup",
      "repeatTime:3": -1,
      "globalShare:1": 1,
      "questLogic:8": "AND",
      "repeat_relative:1": 1,
"name:8": "§a§lИндий",
      "isGlobal:1": 0,
      "lockedProgress:1": 0,
      "autoClaim:1": 0,
      "isSilent:1": 0,
"desc:8": "В EV вы можете производить Индий. Индий нельзя найти в форме руды §3 (за исключением очень небольших количеств на Россе)§r.\n\nСначала вам нужно приготовить Индиевый концентрат из очищенной галенитовой и сфалеритовой руды, затем смешать с небольшим количеством алюминия, чтобы получить Индий. Индий будет использоваться в больших количествах позже, автоматизируйте это как можно скорее.\n\nВы также получаете свинец, цинк, серебро, серу и воду из раствора свинца-цинка. Так что дело не в том, что вы вообще не получаете материалов из руд, просто их меньше."
    }
  },
  "tasks:9": {
    "0:10": {
      "partialMatch:1": 1,
      "autoConsume:1": 0,
      "groupDetect:1": 0,
      "ignoreNBT:1": 0,
      "index:3": 0,
      "consume:1": 0,
      "requiredItems:9": {
        "0:10": {
          "id:8": "gregtech:gt.metaitem.01",
          "Count:3": 9,
          "Damage:2": 6839,
          "OreDict:8": ""
        },
        "1:10": {
          "id:8": "gregtech:gt.metaitem.01",
          "Count:3": 27,
          "Damage:2": 6830,
          "OreDict:8": ""
        },
        "2:10": {
          "id:8": "gregtech:gt.metaitem.01",
          "Count:3": 36,
          "Damage:2": 30720,
          "OreDict:8": ""
        }
      },
      "taskID:8": "bq_standard:optional_retrieval"
    },
    "1:10": {
      "partialMatch:1": 1,
      "autoConsume:1": 0,
      "groupDetect:1": 0,
      "ignoreNBT:1": 0,
      "index:3": 1,
      "consume:1": 0,
      "requiredItems:9": {
        "0:10": {
          "id:8": "gregtech:gt.metaitem.01",
          "Count:3": 36,
          "Damage:2": 2019,
          "OreDict:8": ""
        }
      },
      "taskID:8": "bq_standard:optional_retrieval"
    },
    "2:10": {
      "partialMatch:1": 1,
      "autoConsume:1": 0,
      "groupDetect:1": 0,
      "ignoreNBT:1": 0,
      "index:3": 2,
      "consume:1": 0,
      "requiredItems:9": {
        "0:10": {
          "id:8": "gregtech:gt.metaitem.01",
          "Count:3": 1,
          "Damage:2": 2056,
          "OreDict:8": ""
        }
      },
      "taskID:8": "bq_standard:retrieval"
    }
  },
  "rewards:9": {
    "0:10": {
      "rewardID:8": "bq_standard:item",
      "index:3": 0,
      "rewards:9": {
        "0:10": {
          "id:8": "miscutils:MU-metaitem.01",
          "Count:3": 1,
          "Damage:2": 32054,
          "OreDict:8": ""
        },
        "1:10": {
          "id:8": "enhancedlootbags:lootbag",
          "Count:3": 1,
          "Damage:2": 7,
          "OreDict:8": ""
        }
      }
    },
    "1:10": {
      "rewardID:8": "bq_standard:item",
      "index:3": 1,
      "rewards:9": {
        "0:10": {
          "id:8": "dreamcraft:item.CoinChemistII",
          "Count:3": 1,
          "Damage:2": 0,
          "OreDict:8": ""
        },
        "1:10": {
          "id:8": "dreamcraft:item.CoinTechnicianII",
          "Count:3": 1,
          "Damage:2": 0,
          "OreDict:8": ""
        }
      }
    }
  }
}
