{
  "questIDHigh:4": 0,
  "preRequisites:9": {
    "0:10": {
      "questIDHigh:4": 0,
      "questIDLow:4": 3096
    }
  },
  "questIDLow:4": 3097,
  "properties:10": {
    "betterquesting:10": {
      "snd_complete:8": "random.levelup",
      "taskLogic:8": "AND",
      "visibility:8": "NORMAL",
      "isMain:1": 0,
      "simultaneous:1": 0,
      "icon:10": {
        "id:8": "Railcraft:machine.beta",
        "Count:3": 1,
        "Damage:2": 5,
        "OreDict:8": ""
      },
      "snd_update:8": "random.levelup",
      "repeatTime:3": -1,
      "globalShare:1": 0,
      "questLogic:8": "AND",
      "repeat_relative:1": 1,
"name:8": "Две большие духовки",
      "lockedProgress:1": 0,
      "autoClaim:1": 0,
      "isSilent:1": 0,
"desc:8": "Благодаря 24 автоматизированным коксовым печам вы можете бесконечно поддерживать работу двух больших котлов. Котлы, которые вы хотите построить для этого, — это, в частности, железнодорожные котлы низкого давления, сделанные из железа, каждый из которых настолько велик, насколько это возможно, размером 3х4х3 из котельных резервуаров. Эти мультиблоки стоят дорого, но у вас будет достаточно энергии, и вы израсходуете весь креозот из ваших коксовых печей, чтобы они работали постоянно.\n\nОднако у этих котлов есть вариант высокого давления, для которого требуется гораздо больше стали, чем для их более дешевых аналогов, но который может производить гораздо больше пара. Если вы каким-то образом собрали много стопок стальных слитков, вы можете подумать о том, чтобы попытаться это сделать, но имейте в виду, что ваша установка коксовой печи не может выдержать нагрузку, необходимую этим нагретым гигантам для продолжения работы. То же самое относится и к Большому бронзовому котлу, собственному способу GregTech улучшить ваши крошечные котлы, но с двумя дополнительными проблемами: вы не можете производить древесный уголь достаточно быстро для него (выходная скорость вашей установки составляет 3,75 секунды на древесный уголь, LBB требуется каждые 2 секунды), и он имеет ужасную эффективность для вашего креозота, а это означает, что большая часть его энергии будет потрачена впустую. §6И, возможно, LBB имеет СН по схеме, по сравнению с котлом, который имеет раннее НН из-за стали.§r\n\nОднако сюрприз! Полужидкостные генераторы GT работают, и они очень эффективны с креозотом. Вы можете использовать некоторые из них в сочетании с Большим бронзовым котлом, но вы все равно столкнетесь с проблемой недостаточного производства древесного угля, если вы ничего с этим не сделаете. Вы можете выбрать это как вариант и выполнить этот квест, но это более «экспериментальная» альтернатива."
    }
  },
  "tasks:9": {
    "0:10": {
      "partialMatch:1": 1,
      "autoConsume:1": 0,
      "groupDetect:1": 0,
      "ignoreNBT:1": 1,
      "index:3": 0,
      "consume:1": 0,
      "requiredItems:9": {
        "0:10": {
          "id:8": "Railcraft:machine.beta",
          "Count:3": 9,
          "Damage:2": 6,
          "OreDict:8": ""
        },
        "1:10": {
          "id:8": "Railcraft:machine.beta",
          "Count:3": 9,
          "Damage:2": 5,
          "OreDict:8": ""
        },
        "2:10": {
          "id:8": "Railcraft:machine.beta",
          "Count:3": 72,
          "Damage:2": 3,
          "OreDict:8": ""
        }
      },
      "taskID:8": "bq_standard:optional_retrieval"
    },
    "1:10": {
      "partialMatch:1": 1,
      "autoConsume:1": 0,
      "groupDetect:1": 0,
      "ignoreNBT:1": 1,
      "index:3": 1,
      "consume:1": 0,
      "requiredItems:9": {
        "0:10": {
          "id:8": "gregtech:gt.blockmachines",
          "Count:3": 1,
          "Damage:2": 1020,
          "OreDict:8": ""
        },
        "1:10": {
          "id:8": "gregtech:gt.blockmachines",
          "Count:3": 2,
          "Damage:2": 837,
          "OreDict:8": ""
        }
      },
      "taskID:8": "bq_standard:optional_retrieval"
    },
    "2:10": {
      "partialMatch:1": 1,
      "autoConsume:1": 0,
      "groupDetect:1": 0,
      "ignoreNBT:1": 1,
      "index:3": 2,
      "consume:1": 0,
      "requiredItems:9": {
        "0:10": {
          "id:8": "gregtech:gt.blockgem3",
          "Count:3": 128,
          "Damage:2": 4,
          "OreDict:8": ""
        }
      },
      "taskID:8": "bq_standard:retrieval"
    }
  },
  "rewards:9": {
    "0:10": {
      "rewardID:8": "bq_standard:choice",
      "index:3": 0,
      "choices:9": {
        "0:10": {
          "id:8": "enhancedlootbags:lootbag",
          "Count:3": 1,
          "Damage:2": 4,
          "OreDict:8": ""
        },
        "1:10": {
          "id:8": "Railcraft:fuel.coke",
          "Count:3": 16,
          "Damage:2": 0,
          "OreDict:8": ""
        }
      }
    },
    "1:10": {
      "rewardID:8": "bq_standard:item",
      "index:3": 1,
      "rewards:9": {
        "0:10": {
          "id:8": "dreamcraft:item.CoinTechnician",
          "Count:3": 4,
          "Damage:2": 0,
          "OreDict:8": ""
        }
      }
    }
  }
}
